html_wrapper/__init__.py
html_wrapper/wrapper.py
html_wrapper-0.3.3.dist-info/LICENSE
html_wrapper-0.3.3.dist-info/METADATA
html_wrapper-0.3.3.dist-info/WHEEL
html_wrapper-0.3.3.dist-info/top_level.txt
html_wrapper-0.3.3.dist-info/zip-safe
html_wrapper-0.3.3.dist-info/RECORD
